opencre_lib/__init__.py
opencre_lib/compare.py
opencre_lib-0.1.2.dist-info/METADATA
opencre_lib-0.1.2.dist-info/WHEEL
opencre_lib-0.1.2.dist-info/RECORD
