Metadata-Version: 2.1
Name: opencre-lib
Version: 0.1.2
Summary: This library use the API, from OPENCRE to get compare between standards. Ex.: CWE ASVS SAMM
License: MIT
Author: Cristiano Henrique dos Santos
Author-email: cristianovisk@gmail.com
Requires-Python: >=3.10,<4.0
Classifier: License :: OSI Approved :: MIT License
Classifier: Programming Language :: Python :: 3
Classifier: Programming Language :: Python :: 3.10
Classifier: Programming Language :: Python :: 3.11
Classifier: Programming Language :: Python :: 3.12
Requires-Dist: httpx (>=0.27.2,<0.28.0)
Requires-Dist: rich (>=13.9.4,<14.0.0)
Project-URL: Bug Tracker, https://github.com/cristianovisk/opencre_lib/issues
Project-URL: Código, https://github.com/cristianovisk/opencre_lib
Project-URL: Documentação, https://github.com/cristianovisk/opencre_lib/blob/main/README.md
